ask2api.py
ask2api-1.1.3.dist-info/METADATA
ask2api-1.1.3.dist-info/WHEEL
ask2api-1.1.3.dist-info/entry_points.txt
ask2api-1.1.3.dist-info/licenses/LICENSE
ask2api-1.1.3.dist-info/RECORD
