Metadata-Version: 2.4
Name: ask2api
Version: 1.1.3
Summary: A minimal CLI tool that turns natural language into instant APIs.
Project-URL: Homepage, https://github.com/atasoglu/ask2api
Project-URL: Repository, https://github.com/atasoglu/ask2api.git
Author-email: Ahmet Atasoglu <ahmetatasoglu98@gmail.com>
License: MIT
License-File: LICENSE
Requires-Python: >=3.9
Requires-Dist: requests
Provides-Extra: dev
Requires-Dist: pre-commit; extra == 'dev'
